scolengo_api/__init__.py
scolengo_api/errors.py
scolengo_api/main.py
scolengo_api-1.0.dist-info/METADATA
scolengo_api-1.0.dist-info/WHEEL
scolengo_api-1.0.dist-info/top_level.txt
scolengo_api-1.0.dist-info/RECORD
