Metadata-Version: 2.1
Name: scolengo-api
Version: 1.0
Summary: Unofficial Python API client of Skolengo EMS v2
Home-page: https://github.com/Vermylion/scolengo-api-py
Author: Vermylion
Author-email: vermylioncode@gmail.com
Project-URL: Bug Tracker, https://github.com/Vermylion/scolengo-api-py
Classifier: Programming Language :: Python :: 3
Classifier: License :: OSI Approved :: GNU General Public License v3 (GPLv3)
Classifier: Operating System :: OS Independent
Requires-Python: >=3.7
Requires-Dist: requests
Requires-Dist: authlib
Requires-Dist: json_api_doc
